ob_graphql/__init__.py
ob_graphql/client.py
ob_graphql/exception.py
ob_graphql/message.py
ob_graphql/py.typed
ob_graphql-0.0.1.dist-info/LICENSE
ob_graphql-0.0.1.dist-info/WHEEL
ob_graphql-0.0.1.dist-info/METADATA
ob_graphql-0.0.1.dist-info/RECORD
