Metadata-Version: 2.1
Name: ob_graphql
Version: 0.0.1
Summary: A simple GraphQL client that works over Websocket as the transport protocol, instead of HTTP.
Home-page: https://github.com/obytes/ob-graphql
Author: Yasser Tahiri
Author-email: yasserth19@gmail.com
Requires-Python: >=3.8
Classifier: License :: OSI Approved :: MIT License
Classifier: Operating System :: OS Independent
Classifier: Intended Audience :: Developers
Classifier: Programming Language :: Python
Classifier: Programming Language :: Python :: 3.8
Classifier: Programming Language :: Python :: 3.9
Classifier: Programming Language :: Python :: 3.10
Classifier: Programming Language :: Python :: 3 :: Only
Classifier: Topic :: Utilities
Classifier: Typing :: Typed
Requires-Dist: websocket-client
Requires-Dist: mkdocs ; extra == "docs"
Requires-Dist: mkdocs-markdownextradata-plugin ; extra == "docs"
Requires-Dist: mkdocs-material ; extra == "docs"
Requires-Dist: jinja2 ; extra == "docs"
Requires-Dist: mkdocs-mermaid2-plugin ; extra == "docs"
Requires-Dist: markdown-include ; extra == "docs"
Requires-Dist: pymdown-extensions ; extra == "docs"
Requires-Dist: mdx-include ; extra == "docs"
Requires-Dist: pre-commit==2.18.0 ; extra == "lint"
Provides-Extra: docs
Provides-Extra: lint
